Workbook

Sheet Premissas
A1: Premissa | B1: Valor | C1: Observação
A2: desconto_pix_roma | B2: 0.06 | C2: Informado pelo Lucas: 6% de desconto no PIX
A3: parcelas_roma | B3: 6 | C3: Informado pelo Lucas: até 6x sem juros
A4: limite_classificacao | B4: 0.05 | C4: Acima de +5% = Caro; abaixo de -5% = Competitivo; entre = Na média
A5: data_base | B5: 2026-09-23 | C5: preço cheio = preço "de" (riscado) ou, sem riscado, o total parcelado. Cinza = sem dado
A6: desconto_parcelado_roma | B6: 0.06 | C6: Informado pelo Lucas: o desconto de 6% vale em qualquer forma de pagamento, inclusive parcelado em 6x

Sheet Politicas_Pagamento
A1: loja | B1: desconto_pix | C1: parcelas_sem_juros | D1: observacao
A2: Roma | B2: =Premissas!B2 -> 0.06 | C2: =Premissas!B3 -> 6 | D2: 6% de desconto em qualquer forma de pagamento (PIX ou 6x sem juros)
A3: PneuStore | B3: 0.1 | C3: 10 | D3: 10% OFF no PIX (real varia por item); parcelado = preço cheio
A4: HC Pneus | B4: 0.03 | C4: 6 | D4: Promoção de 20% OFF sobre o preço riscado; 3% extra à vista
A5: Achei Pneus | B5: 0.12 | C5: 12 | D5: 12% no PIX; parcelado = preço cheio

Sheet PneuStore
A1: item | B1: medida | C1: modelo | D1: sku_roma | E1: data_coleta | F1: concorrente | G1: roma_preco_cheio | H1: roma_preco_pix | I1: roma_preco_parcelado | J1: roma_n_parcelas | K1: roma_valor_parcela | L1: nome_anuncio_concorrente | M1: conc_preco_cheio | N1: conc_preco_pix | O1: conc_preco_parcelado | P1: conc_n_parcelas | Q1: conc_valor_parcela | R1: conc_desconto_pix_pct | S1: conc_desconto_parcelado_pct | T1: dif_pix_pct | U1: dif_parcelado_pct | V1: dif_parcela_pct | W1: classificacao_pix
A2: 1 | B2: 175/65R14 | C2: Kelly Edge Touring 2 | D2: 924096 | E2: 2026-09-23 | F2: PneuStore | G2: 306.81 | H2: =ROUND(G2*(1-Premissas!$B$2),2) -> 288.4 | I2: =ROUND(G2*(1-Premissas!$B$6),2) -> 288.4 | J2: =Premissas!$B$3 -> 6 | K2: =ROUND(I2/J2,2) -> 48.07 | L2: Pneu Kelly by Goodyear Aro 14 Edge Touring 2 175/65R14 86H XL | M2: 355.45 | N2: 319.9 | O2: 355.45 | P2: 10 | Q2: =IF(N2="","",ROUND(O2/P2,2)) -> 35.55 | R2: =IF(N2="","",1-N2/M2) -> 0.10001407 | S2: =IF(N2="","",1-O2/M2) -> 0 | T2: =IF(N2="","",H2/N2-1) -> -0.098468271 | U2: =IF(N2="","",I2/O2-1) -> -0.18863413 | V2: =IF(N2="","",K2/Q2-1) -> 0.35218003 | W2: =IF(T2="","Sem dado",IF(T2>Premissas!$B$4,"Caro",IF(T2<-Premissas!$B$4,"Competitivo","Na média"))) -> Competitivo
A3: 2 | B3: 185/60R15 | C3: Edge Sport 2 | D3: 1452 | E3: 2026-09-23 | F3: PneuStore | G3: 423.06 | H3: =ROUND(G3*(1-Premissas!$B$2),2) -> 397.68 | I3: =ROUND(G3*(1-Premissas!$B$6),2) -> 397.68 | J3: =Premissas!$B$3 -> 6 | K3: =ROUND(I3/J3,2) -> 66.28 | L3: Pneu Kelly by Goodyear Aro 15 Edge Sport 2 185/60R15 88H XL | M3: 481.59 | N3: 394.9 | O3: 481.59 | P3: 10 | Q3: =IF(N3="","",ROUND(O3/P3,2)) -> 48.16 | R3: =IF(N3="","",1-N3/M3) -> 0.18000789 | S3: =IF(N3="","",1-O3/M3) -> 0 | T3: =IF(N3="","",H3/N3-1) -> 0.0070397569 | U3: =IF(N3="","",I3/O3-1) -> -0.17423535 | V3: =IF(N3="","",K3/Q3-1) -> 0.37624585 | W3: =IF(T3="","Sem dado",IF(T3>Premissas!$B$4,"Caro",IF(T3<-Premissas!$B$4,"Competitivo","Na média"))) -> Na média
A4: 3 | B4: 205/65R16 | C4: EfficientGrip SUV | D4: 923983 | E4: 2026-09-23 | F4: PneuStore | G4: 619.29 | H4: =ROUND(G4*(1-Premissas!$B$2),2) -> 582.13 | I4: =ROUND(G4*(1-Premissas!$B$6),2) -> 582.13 | J4: =Premissas!$B$3 -> 6 | K4: =ROUND(I4/J4,2) -> 97.02 | L4: Pneu Goodyear Aro 16 EfficientGrip SUV 205/65R16 95H | M4: 755.45 | N4: 679.9 | O4: 755.45 | P4: 10 | Q4: =IF(N4="","",ROUND(O4/P4,2)) -> 75.55 | R4: =IF(N4="","",1-N4/M4) -> 0.10000662 | S4: =IF(N4="","",1-O4/M4) -> 0 | T4: =IF(N4="","",H4/N4-1) -> -0.14380056 | U4: =IF(N4="","",I4/O4-1) -> -0.22942617 | V4: =IF(N4="","",K4/Q4-1) -> 0.28418266 | W4: =IF(T4="","Sem dado",IF(T4>Premissas!$B$4,"Caro",IF(T4<-Premissas!$B$4,"Competitivo","Na média"))) -> Competitivo
A5: 4 | B5: 175/65R14 | C5: Assurance Maxlife | D5: 923865 | E5: 2026-09-23 | F5: PneuStore | G5: 353.31 | H5: =ROUND(G5*(1-Premissas!$B$2),2) -> 332.11 | I5: =ROUND(G5*(1-Premissas!$B$6),2) -> 332.11 | J5: =Premissas!$B$3 -> 6 | K5: =ROUND(I5/J5,2) -> 55.35 | L5: Pneu Goodyear Aro 14 Assurance Maxlife 175/65R14 86H XL | M5: 397.62 | N5: 349.9 | O5: 397.62 | P5: 10 | Q5: =IF(N5="","",ROUND(O5/P5,2)) -> 39.76 | R5: =IF(N5="","",1-N5/M5) -> 0.12001408 | S5: =IF(N5="","",1-O5/M5) -> 0 | T5: =IF(N5="","",H5/N5-1) -> -0.050843098 | U5: =IF(N5="","",I5/O5-1) -> -0.16475529 | V5: =IF(N5="","",K5/Q5-1) -> 0.39210262 | W5: =IF(T5="","Sem dado",IF(T5>Premissas!$B$4,"Caro",IF(T5<-Premissas!$B$4,"Competitivo","Na média"))) -> Competitivo
A6: 5 | B6: 175/70R13 | C6: Edge Touring 2 | D6: 924049 | E6: 2026-09-23 | F6: PneuStore | G6: 297.51 | H6: =ROUND(G6*(1-Premissas!$B$2),2) -> 279.66 | I6: =ROUND(G6*(1-Premissas!$B$6),2) -> 279.66 | J6: =Premissas!$B$3 -> 6 | K6: =ROUND(I6/J6,2) -> 46.61 | L6: Pneu Kelly By Goodyear Aro 13 Edge Touring 2 175/70R13 82T | M6: 340.8 | N6: 299.9 | O6: 340.8 | P6: 10 | Q6: =IF(N6="","",ROUND(O6/P6,2)) -> 34.08 | R6: =IF(N6="","",1-N6/M6) -> 0.12001174 | S6: =IF(N6="","",1-O6/M6) -> 0 | T6: =IF(N6="","",H6/N6-1) -> -0.067489163 | U6: =IF(N6="","",I6/O6-1) -> -0.17940141 | V6: =IF(N6="","",K6/Q6-1) -> 0.36766432 | W6: =IF(T6="","Sem dado",IF(T6>Premissas!$B$4,"Caro",IF(T6<-Premissas!$B$4,"Competitivo","Na média"))) -> Competitivo
A7: 6 | B7: 185/65R15 | C7: Edge Sport 2 | D7: 1445 | E7: 2026-09-23 | F7: PneuStore | G7: 433.29 | H7: =ROUND(G7*(1-Premissas!$B$2),2) -> 407.29 | I7: =ROUND(G7*(1-Premissas!$B$6),2) -> 407.29 | J7: =Premissas!$B$3 -> 6 | K7: =ROUND(I7/J7,2) -> 67.88 | L7: Pneu Kelly by Goodyear Aro 15 Edge Sport 2 185/65R15 88H | M7: 512.08 | N7: 419.9 | O7: 512.08 | P7: 10 | Q7: =IF(N7="","",ROUND(O7/P7,2)) -> 51.21 | R7: =IF(N7="","",1-N7/M7) -> 0.18001094 | S7: =IF(N7="","",1-O7/M7) -> 0 | T7: =IF(N7="","",H7/N7-1) -> -0.03003096 | U7: =IF(N7="","",I7/O7-1) -> -0.20463599 | V7: =IF(N7="","",K7/Q7-1) -> 0.32552236 | W7: =IF(T7="","Sem dado",IF(T7>Premissas!$B$4,"Caro",IF(T7<-Premissas!$B$4,"Competitivo","Na média"))) -> Na média
A8: 7 | B8: 225/75R16C | C8: Cargo Marathon 2 | D8: 923825 | E8: 2026-09-23 | F8: PneuStore | G8: 1097.31 | H8: =ROUND(G8*(1-Premissas!$B$2),2) -> 1031.47 | I8: =ROUND(G8*(1-Premissas!$B$6),2) -> 1031.47 | J8: =Premissas!$B$3 -> 6 | K8: =ROUND(I8/J8,2) -> 171.91 | L8: Pneu Goodyear Aro 16 Cargo Marathon 2 225/75R16C 118/116R 10 Lonas | M8: 1299.89 | N8: 1169.9 | O8: 1299.89 | P8: 10 | Q8: =IF(N8="","",ROUND(O8/P8,2)) -> 129.99 | R8: =IF(N8="","",1-N8/M8) -> 0.10000077 | S8: =IF(N8="","",1-O8/M8) -> 0 | T8: =IF(N8="","",H8/N8-1) -> -0.11832635 | U8: =IF(N8="","",I8/O8-1) -> -0.2064944 | V8: =IF(N8="","",K8/Q8-1) -> 0.32248635 | W8: =IF(T8="","Sem dado",IF(T8>Premissas!$B$4,"Caro",IF(T8<-Premissas!$B$4,"Competitivo","Na média"))) -> Competitivo
A9: 8 | B9: 215/55R17 | C9: EfficientGrip SUV | D9: 2081 | E9: 2026-09-23 | F9: PneuStore | G9: 702.99 | H9: =ROUND(G9*(1-Premissas!$B$2),2) -> 660.81 | I9: =ROUND(G9*(1-Premissas!$B$6),2) -> 660.81 | J9: =Premissas!$B$3 -> 6 | K9: =ROUND(I9/J9,2) -> 110.14 | L9: Pneu Goodyear Aro 17 EfficientGrip SUV 215/55R17 94V | M9: 749.89 | N9: 659.9 | O9: 749.89 | P9: 10 | Q9: =IF(N9="","",ROUND(O9/P9,2)) -> 74.99 | R9: =IF(N9="","",1-N9/M9) -> 0.12000427 | S9: =IF(N9="","",1-O9/M9) -> 0 | T9: =IF(N9="","",H9/N9-1) -> 0.0013789968 | U9: =IF(N9="","",I9/O9-1) -> -0.11879076 | V9: =IF(N9="","",K9/Q9-1) -> 0.46872916 | W9: =IF(T9="","Sem dado",IF(T9>Premissas!$B$4,"Caro",IF(T9<-Premissas!$B$4,"Competitivo","Na média"))) -> Na média
A10: 9 | B10: 185/65R15 | C10: Eagle Sport 2 | D10: 923978 | E10: 2026-09-23 | F10: PneuStore | G10: 483.51 | H10: =ROUND(G10*(1-Premissas!$B$2),2) -> 454.5 | I10: =ROUND(G10*(1-Premissas!$B$6),2) -> 454.5 | J10: =Premissas!$B$3 -> 6 | K10: =ROUND(I10/J10,2) -> 75.75 | L10: Pneu Goodyear Aro 15 Eagle Sport 2 185/65R15 88H | M10: 533.23 | N10: 479.9 | O10: 533.23 | P10: 10 | Q10: =IF(N10="","",ROUND(O10/P10,2)) -> 53.32 | R10: =IF(N10="","",1-N10/M10) -> 0.10001313 | S10: =IF(N10="","",1-O10/M10) -> 0 | T10: =IF(N10="","",H10/N10-1) -> -0.052927693 | U10: =IF(N10="","",I10/O10-1) -> -0.14764736 | V10: =IF(N10="","",K10/Q10-1) -> 0.42066767 | W10: =IF(T10="","Sem dado",IF(T10>Premissas!$B$4,"Caro",IF(T10<-Premissas!$B$4,"Competitivo","Na média"))) -> Competitivo

Sheet HC_Pneus
A1: item | B1: medida | C1: modelo | D1: sku_roma | E1: data_coleta | F1: concorrente | G1: roma_preco_cheio | H1: roma_preco_pix | I1: roma_preco_parcelado | J1: roma_n_parcelas | K1: roma_valor_parcela | L1: nome_anuncio_concorrente | M1: conc_preco_cheio | N1: conc_preco_pix | O1: conc_preco_parcelado | P1: conc_n_parcelas | Q1: conc_valor_parcela | R1: conc_desconto_pix_pct | S1: conc_desconto_parcelado_pct | T1: dif_pix_pct | U1: dif_parcelado_pct | V1: dif_parcela_pct | W1: classificacao_pix
A2: 1 | B2: 175/65R14 | C2: Kelly Edge Touring 2 | D2: 924096 | E2: 2026-09-23 | F2: HC Pneus | G2: 306.81 | H2: =ROUND(G2*(1-Premissas!$B$2),2) -> 288.4 | I2: =ROUND(G2*(1-Premissas!$B$6),2) -> 288.4 | J2: =Premissas!$B$3 -> 6 | K2: =ROUND(I2/J2,2) -> 48.07 | L2: Pneu 175/65R14 86H Goodyear Kelly Edge Touring 2 | M2: 435.72 | N2: 338.12 | O2: 348.58 | P2: 6 | Q2: =IF(N2="","",ROUND(O2/P2,2)) -> 58.1 | R2: =IF(N2="","",1-N2/M2) -> 0.22399706 | S2: =IF(N2="","",1-O2/M2) -> 0.19999082 | T2: =IF(N2="","",H2/N2-1) -> -0.14704839 | U2: =IF(N2="","",I2/O2-1) -> -0.1726433 | V2: =IF(N2="","",K2/Q2-1) -> -0.17263339 | W2: =IF(T2="","Sem dado",IF(T2>Premissas!$B$4,"Caro",IF(T2<-Premissas!$B$4,"Competitivo","Na média"))) -> Competitivo
A3: 2 | B3: 185/60R15 | C3: Edge Sport 2 | D3: 1452 | E3: 2026-09-23 | F3: HC Pneus | G3: 423.06 | H3: =ROUND(G3*(1-Premissas!$B$2),2) -> 397.68 | I3: =ROUND(G3*(1-Premissas!$B$6),2) -> 397.68 | J3: =Premissas!$B$3 -> 6 | K3: =ROUND(I3/J3,2) -> 66.28 | L3: Pneu 185/60R15 88H Goodyear Kelly Edge Sport 2 | M3: 583.62 | N3: 452.89 | O3: 466.9 | P3: 6 | Q3: =IF(N3="","",ROUND(O3/P3,2)) -> 77.82 | R3: =IF(N3="","",1-N3/M3) -> 0.22399849 | S3: =IF(N3="","",1-O3/M3) -> 0.19999315 | T3: =IF(N3="","",H3/N3-1) -> -0.12190598 | U3: =IF(N3="","",I3/O3-1) -> -0.14825444 | V3: =IF(N3="","",K3/Q3-1) -> -0.14829093 | W3: =IF(T3="","Sem dado",IF(T3>Premissas!$B$4,"Caro",IF(T3<-Premissas!$B$4,"Competitivo","Na média"))) -> Competitivo
A4: 3 | B4: 205/65R16 | C4: EfficientGrip SUV | D4: 923983 | E4: 2026-09-23 | F4: HC Pneus | G4: 619.29 | H4: =ROUND(G4*(1-Premissas!$B$2),2) -> 582.13 | I4: =ROUND(G4*(1-Premissas!$B$6),2) -> 582.13 | J4: =Premissas!$B$3 -> 6 | K4: =ROUND(I4/J4,2) -> 97.02 | L4: Pneu 205/65R16 95H Goodyear EfficientGrip SUV | M4: 847.48 | N4: 657.64 | O4: 677.98 | P4: 6 | Q4: =IF(N4="","",ROUND(O4/P4,2)) -> 113 | R4: =IF(N4="","",1-N4/M4) -> 0.22400529 | S4: =IF(N4="","",1-O4/M4) -> 0.20000472 | T4: =IF(N4="","",H4/N4-1) -> -0.11481966 | U4: =IF(N4="","",I4/O4-1) -> -0.14137585 | V4: =IF(N4="","",K4/Q4-1) -> -0.14141593 | W4: =IF(T4="","Sem dado",IF(T4>Premissas!$B$4,"Caro",IF(T4<-Premissas!$B$4,"Competitivo","Na média"))) -> Competitivo
A5: 4 | B5: 175/65R14 | C5: Assurance Maxlife | D5: 923865 | E5: 2026-09-23 | F5: HC Pneus | G5: 353.31 | H5: =ROUND(G5*(1-Premissas!$B$2),2) -> 332.11 | I5: =ROUND(G5*(1-Premissas!$B$6),2) -> 332.11 | J5: =Premissas!$B$3 -> 6 | K5: =ROUND(I5/J5,2) -> 55.35 | L5: Pneu 175/65R14 86H Goodyear Assurance MaxLife | M5: 484.64 | N5: 376.08 | O5: 387.71 | P5: 6 | Q5: =IF(N5="","",ROUND(O5/P5,2)) -> 64.62 | R5: =IF(N5="","",1-N5/M5) -> 0.22400132 | S5: =IF(N5="","",1-O5/M5) -> 0.20000413 | T5: =IF(N5="","",H5/N5-1) -> -0.11691661 | U5: =IF(N5="","",I5/O5-1) -> -0.14340615 | V5: =IF(N5="","",K5/Q5-1) -> -0.14345404 | W5: =IF(T5="","Sem dado",IF(T5>Premissas!$B$4,"Caro",IF(T5<-Premissas!$B$4,"Competitivo","Na média"))) -> Competitivo
A6: 5 | B6: 175/70R13 | C6: Edge Touring 2 | D6: 924049 | E6: 2026-09-23 | F6: HC Pneus | G6: 297.51 | H6: =ROUND(G6*(1-Premissas!$B$2),2) -> 279.66 | I6: =ROUND(G6*(1-Premissas!$B$6),2) -> 279.66 | J6: =Premissas!$B$3 -> 6 | K6: =ROUND(I6/J6,2) -> 46.61 | L6: Pneu 175/70R13 82T Goodyear Kelly Edge Touring 2 | M6: 405.85 | N6: 314.94 | O6: 324.68 | P6: 6 | Q6: =IF(N6="","",ROUND(O6/P6,2)) -> 54.11 | R6: =IF(N6="","",1-N6/M6) -> 0.22399901 | S6: =IF(N6="","",1-O6/M6) -> 0.2 | T6: =IF(N6="","",H6/N6-1) -> -0.11202134 | U6: =IF(N6="","",I6/O6-1) -> -0.1386596 | V6: =IF(N6="","",K6/Q6-1) -> -0.13860654 | W6: =IF(T6="","Sem dado",IF(T6>Premissas!$B$4,"Caro",IF(T6<-Premissas!$B$4,"Competitivo","Na média"))) -> Competitivo
A7: 6 | B7: 185/65R15 | C7: Edge Sport 2 | D7: 1445 | E7: 2026-09-23 | F7: HC Pneus | G7: 433.29 | H7: =ROUND(G7*(1-Premissas!$B$2),2) -> 407.29 | I7: =ROUND(G7*(1-Premissas!$B$6),2) -> 407.29 | J7: =Premissas!$B$3 -> 6 | K7: =ROUND(I7/J7,2) -> 67.88 | L7: Pneu 185/65R15 88H Goodyear Kelly Edge Sport 2 | M7: 597.92 | N7: 463.99 | O7: 478.34 | P7: 6 | Q7: =IF(N7="","",ROUND(O7/P7,2)) -> 79.72 | R7: =IF(N7="","",1-N7/M7) -> 0.22399318 | S7: =IF(N7="","",1-O7/M7) -> 0.19999331 | T7: =IF(N7="","",H7/N7-1) -> -0.12220091 | U7: =IF(N7="","",I7/O7-1) -> -0.14853452 | V7: =IF(N7="","",K7/Q7-1) -> -0.14851982 | W7: =IF(T7="","Sem dado",IF(T7>Premissas!$B$4,"Caro",IF(T7<-Premissas!$B$4,"Competitivo","Na média"))) -> Competitivo
A8: 7 | B8: 225/75R16C | C8: Cargo Marathon 2 | D8: 923825 | E8: 2026-09-23 | F8: HC Pneus | G8: 1097.31 | H8: =ROUND(G8*(1-Premissas!$B$2),2) -> 1031.47 | I8: =ROUND(G8*(1-Premissas!$B$6),2) -> 1031.47 | J8: =Premissas!$B$3 -> 6 | K8: =ROUND(I8/J8,2) -> 171.91 | L8: Pneu 225/75R16C 118/116R Goodyear Cargo Marathon 2 | M8: 1481.73 | N8: 1149.82 | O8: 1185.38 | P8: 6 | Q8: =IF(N8="","",ROUND(O8/P8,2)) -> 197.56 | R8: =IF(N8="","",1-N8/M8) -> 0.22400167 | S8: =IF(N8="","",1-O8/M8) -> 0.2000027 | T8: =IF(N8="","",H8/N8-1) -> -0.10292915 | U8: =IF(N8="","",I8/O8-1) -> -0.12984022 | V8: =IF(N8="","",K8/Q8-1) -> -0.12983397 | W8: =IF(T8="","Sem dado",IF(T8>Premissas!$B$4,"Caro",IF(T8<-Premissas!$B$4,"Competitivo","Na média"))) -> Competitivo
A9: 8 | B9: 215/55R17 | C9: EfficientGrip SUV | D9: 2081 | E9: 2026-09-23 | F9: HC Pneus | G9: 702.99 | H9: =ROUND(G9*(1-Premissas!$B$2),2) -> 660.81 | I9: =ROUND(G9*(1-Premissas!$B$6),2) -> 660.81 | J9: =Premissas!$B$3 -> 6 | K9: =ROUND(I9/J9,2) -> 110.14 | L9: Pneu 215/55R17 94V Goodyear EfficientGrip SUV | M9: 945.01 | N9: 733.33 | O9: 756.01 | P9: 6 | Q9: =IF(N9="","",ROUND(O9/P9,2)) -> 126 | R9: =IF(N9="","",1-N9/M9) -> 0.22399763 | S9: =IF(N9="","",1-O9/M9) -> 0.19999788 | T9: =IF(N9="","",H9/N9-1) -> -0.098891359 | U9: =IF(N9="","",I9/O9-1) -> -0.12592426 | V9: =IF(N9="","",K9/Q9-1) -> -0.12587302 | W9: =IF(T9="","Sem dado",IF(T9>Premissas!$B$4,"Caro",IF(T9<-Premissas!$B$4,"Competitivo","Na média"))) -> Competitivo
A10: 9 | B10: 185/65R15 | C10: Eagle Sport 2 | D10: 923978 | E10: 2026-09-23 | F10: HC Pneus | G10: 483.51 | H10: =ROUND(G10*(1-Premissas!$B$2),2) -> 454.5 | I10: =ROUND(G10*(1-Premissas!$B$6),2) -> 454.5 | J10: =Premissas!$B$3 -> 6 | K10: =ROUND(I10/J10,2) -> 75.75 | L10: Pneu 185/65R15 88H Goodyear Eagle Sport 2 | M10: 664.42 | N10: 515.59 | O10: 531.54 | P10: 6 | Q10: =IF(N10="","",ROUND(O10/P10,2)) -> 88.59 | R10: =IF(N10="","",1-N10/M10) -> 0.22399988 | S10: =IF(N10="","",1-O10/M10) -> 0.19999398 | T10: =IF(N10="","",H10/N10-1) -> -0.11848562 | U10: =IF(N10="","",I10/O10-1) -> -0.14493735 | V10: =IF(N10="","",K10/Q10-1) -> -0.14493735 | W10: =IF(T10="","Sem dado",IF(T10>Premissas!$B$4,"Caro",IF(T10<-Premissas!$B$4,"Competitivo","Na média"))) -> Competitivo

Sheet Achei_Pneus
A1: item | B1: medida | C1: modelo | D1: sku_roma | E1: data_coleta | F1: concorrente | G1: roma_preco_cheio | H1: roma_preco_pix | I1: roma_preco_parcelado | J1: roma_n_parcelas | K1: roma_valor_parcela | L1: nome_anuncio_concorrente | M1: conc_preco_cheio | N1: conc_preco_pix | O1: conc_preco_parcelado | P1: conc_n_parcelas | Q1: conc_valor_parcela | R1: conc_desconto_pix_pct | S1: conc_desconto_parcelado_pct | T1: dif_pix_pct | U1: dif_parcelado_pct | V1: dif_parcela_pct | W1: classificacao_pix | X1: link
A2: 1 | B2: 175/65R14 | C2: Kelly Edge Touring 2 | D2: 924096 | E2: 2026-09-23 | F2: Achei Pneus | G2: 306.81 | H2: =ROUND(G2*(1-Premissas!$B$2),2) -> 288.4 | I2: =ROUND(G2*(1-Premissas!$B$6),2) -> 288.4 | J2: =Premissas!$B$3 -> 6 | K2: =ROUND(I2/J2,2) -> 48.07 | L2: PNEU 175/65R14 GOODYEAR KELLY EDGE TOURING 2 86H | M2: 351.02 | N2: 308.9 | O2: 351.02 | P2: 12 | Q2: =IF(N2="","",ROUND(O2/P2,2)) -> 29.25 | R2: =IF(N2="","",1-N2/M2) -> 0.11999316 | S2: =IF(N2="","",1-O2/M2) -> 0 | T2: =IF(N2="","",H2/N2-1) -> -0.066364519 | U2: =IF(N2="","",I2/O2-1) -> -0.17839439 | V2: =IF(N2="","",K2/Q2-1) -> 0.6434188 | W2: =IF(T2="","Sem dado",IF(T2>Premissas!$B$4,"Caro",IF(T2<-Premissas!$B$4,"Competitivo","Na média"))) -> Competitivo | X2: print Lucas 23/09
A3: 2 | B3: 185/60R15 | C3: Edge Sport 2 | D3: 1452 | E3: 2026-09-23 | F3: Achei Pneus | G3: 423.06 | H3: =ROUND(G3*(1-Premissas!$B$2),2) -> 397.68 | I3: =ROUND(G3*(1-Premissas!$B$6),2) -> 397.68 | J3: =Premissas!$B$3 -> 6 | K3: =ROUND(I3/J3,2) -> 66.28 | L3: PNEU 185/60R15 GOODYEAR KELLY EDGE SPORT 2 88H | M3: 447.72 | N3: 393.99 | O3: 447.72 | P3: 12 | Q3: =IF(N3="","",ROUND(O3/P3,2)) -> 37.31 | R3: =IF(N3="","",1-N3/M3) -> 0.12000804 | S3: =IF(N3="","",1-O3/M3) -> 0 | T3: =IF(N3="","",H3/N3-1) -> 0.0093657199 | U3: =IF(N3="","",I3/O3-1) -> -0.11176628 | V3: =IF(N3="","",K3/Q3-1) -> 0.77646744 | W3: =IF(T3="","Sem dado",IF(T3>Premissas!$B$4,"Caro",IF(T3<-Premissas!$B$4,"Competitivo","Na média"))) -> Na média | X3: print Lucas 23/09
A4: 3 | B4: 205/65R16 | C4: EfficientGrip SUV | D4: 923983 | E4: 2026-09-23 | F4: Achei Pneus | G4: 619.29 | H4: =ROUND(G4*(1-Premissas!$B$2),2) -> 582.13 | I4: =ROUND(G4*(1-Premissas!$B$6),2) -> 582.13 | J4: =Premissas!$B$3 -> 6 | K4: =ROUND(I4/J4,2) -> 97.02 | L4: PNEU 205/65R16 GOODYEAR EFFICIENTGRIP SUV 95H | M4: 724.99 | N4: 637.99 | O4: 724.99 | P4: 12 | Q4: =IF(N4="","",ROUND(O4/P4,2)) -> 60.42 | R4: =IF(N4="","",1-N4/M4) -> 0.12000166 | S4: =IF(N4="","",1-O4/M4) -> 0 | T4: =IF(N4="","",H4/N4-1) -> -0.087556231 | U4: =IF(N4="","",I4/O4-1) -> -0.19705099 | V4: =IF(N4="","",K4/Q4-1) -> 0.60575968 | W4: =IF(T4="","Sem dado",IF(T4>Premissas!$B$4,"Caro",IF(T4<-Premissas!$B$4,"Competitivo","Na média"))) -> Competitivo | X4: print Lucas 23/09
A5: 4 | B5: 175/65R14 | C5: Assurance Maxlife | D5: 923865 | E5: 2026-09-23 | F5: Achei Pneus | G5: 353.31 | H5: =ROUND(G5*(1-Premissas!$B$2),2) -> 332.11 | I5: =ROUND(G5*(1-Premissas!$B$6),2) -> 332.11 | J5: =Premissas!$B$3 -> 6 | K5: =ROUND(I5/J5,2) -> 55.35 | L5: PNEU 175/65R14 GOODYEAR ASSURANCE MAXLIFE 86H | M5: 395.44 | N5: 347.99 | O5: 395.44 | P5: 12 | Q5: =IF(N5="","",ROUND(O5/P5,2)) -> 32.95 | R5: =IF(N5="","",1-N5/M5) -> 0.11999292 | S5: =IF(N5="","",1-O5/M5) -> 0 | T5: =IF(N5="","",H5/N5-1) -> -0.045633495 | U5: =IF(N5="","",I5/O5-1) -> -0.16015072 | V5: =IF(N5="","",K5/Q5-1) -> 0.67981791 | W5: =IF(T5="","Sem dado",IF(T5>Premissas!$B$4,"Caro",IF(T5<-Premissas!$B$4,"Competitivo","Na média"))) -> Na média | X5: print Lucas 23/09
A6: 5 | B6: 175/70R13 | C6: Edge Touring 2 | D6: 924049 | E6: 2026-09-23 | F6: Achei Pneus | G6: 297.51 | H6: =ROUND(G6*(1-Premissas!$B$2),2) -> 279.66 | I6: =ROUND(G6*(1-Premissas!$B$6),2) -> 279.66 | J6: =Premissas!$B$3 -> 6 | K6: =ROUND(I6/J6,2) -> 46.61 | L6: PNEU 175/70R13 GOODYEAR KELLY EDGE TOURING 2 82T | M6: 338.63 | N6: 297.99 | O6: 338.63 | P6: 12 | Q6: =IF(N6="","",ROUND(O6/P6,2)) -> 28.22 | R6: =IF(N6="","",1-N6/M6) -> 0.12001299 | S6: =IF(N6="","",1-O6/M6) -> 0 | T6: =IF(N6="","",H6/N6-1) -> -0.061512131 | U6: =IF(N6="","",I6/O6-1) -> -0.17414287 | V6: =IF(N6="","",K6/Q6-1) -> 0.65166549 | W6: =IF(T6="","Sem dado",IF(T6>Premissas!$B$4,"Caro",IF(T6<-Premissas!$B$4,"Competitivo","Na média"))) -> Competitivo | X6: https://www.acheipneus.com.br/pneu-17570r13-goodyear-kelly-edge-touring-2-82t
A7: 6 | B7: 185/65R15 | C7: Edge Sport 2 | D7: 1445 | E7: 2026-09-23 | F7: Achei Pneus | G7: 433.29 | H7: =ROUND(G7*(1-Premissas!$B$2),2) -> 407.29 | I7: =ROUND(G7*(1-Premissas!$B$6),2) -> 407.29 | J7: =Premissas!$B$3 -> 6 | K7: =ROUND(I7/J7,2) -> 67.88 | L7: PNEU 185/65R15 GOODYEAR KELLY EDGE SPORT 2 88H | M7: 476.13 | N7: 418.99 | O7: 476.13 | P7: 12 | Q7: =IF(N7="","",ROUND(O7/P7,2)) -> 39.68 | R7: =IF(N7="","",1-N7/M7) -> 0.12000924 | S7: =IF(N7="","",1-O7/M7) -> 0 | T7: =IF(N7="","",H7/N7-1) -> -0.027924294 | U7: =IF(N7="","",I7/O7-1) -> -0.14458236 | V7: =IF(N7="","",K7/Q7-1) -> 0.71068548 | W7: =IF(T7="","Sem dado",IF(T7>Premissas!$B$4,"Caro",IF(T7<-Premissas!$B$4,"Competitivo","Na média"))) -> Na média | X7: print Lucas 23/09
A8: 7 | B8: 225/75R16C | C8: Cargo Marathon 2 | D8: 923825 | E8: 2026-09-23 | F8: Achei Pneus | G8: 1097.31 | H8: =ROUND(G8*(1-Premissas!$B$2),2) -> 1031.47 | I8: =ROUND(G8*(1-Premissas!$B$6),2) -> 1031.47 | J8: =Premissas!$B$3 -> 6 | K8: =ROUND(I8/J8,2) -> 171.91 | L8: PNEU 225/75R16C GOODYEAR CARGO MARATHON 2 118/116R | M8: 1226.14 | N8: 1079 | O8: 1226.14 | P8: 12 | Q8: =IF(N8="","",ROUND(O8/P8,2)) -> 102.18 | R8: =IF(N8="","",1-N8/M8) -> 0.12000261 | S8: =IF(N8="","",1-O8/M8) -> 0 | T8: =IF(N8="","",H8/N8-1) -> -0.044050046 | U8: =IF(N8="","",I8/O8-1) -> -0.15876654 | V8: =IF(N8="","",K8/Q8-1) -> 0.68242317 | W8: =IF(T8="","Sem dado",IF(T8>Premissas!$B$4,"Caro",IF(T8<-Premissas!$B$4,"Competitivo","Na média"))) -> Na média | X8: print Lucas 23/09
A9: 8 | B9: 215/55R17 | C9: EfficientGrip SUV | D9: 2081 | E9: 2026-09-23 | F9: Achei Pneus | G9: 702.99 | H9: =ROUND(G9*(1-Premissas!$B$2),2) -> 660.81 | I9: =ROUND(G9*(1-Premissas!$B$6),2) -> 660.81 | J9: =Premissas!$B$3 -> 6 | K9: =ROUND(I9/J9,2) -> 110.14 | L9: PNEU 215/55R17 GOODYEAR EFFICIENTGRIP SUV 94V | M9: 724.99 | N9: 637.99 | O9: 724.99 | P9: 12 | Q9: =IF(N9="","",ROUND(O9/P9,2)) -> 60.42 | R9: =IF(N9="","",1-N9/M9) -> 0.12000166 | S9: =IF(N9="","",1-O9/M9) -> 0 | T9: =IF(N9="","",H9/N9-1) -> 0.035768586 | U9: =IF(N9="","",I9/O9-1) -> -0.088525359 | V9: =IF(N9="","",K9/Q9-1) -> 0.82290632 | W9: =IF(T9="","Sem dado",IF(T9>Premissas!$B$4,"Caro",IF(T9<-Premissas!$B$4,"Competitivo","Na média"))) -> Na média | X9: print Lucas 23/09
A10: 9 | B10: 185/65R15 | C10: Eagle Sport 2 | D10: 923978 | E10: 2026-09-23 | F10: Achei Pneus | G10: 483.51 | H10: =ROUND(G10*(1-Premissas!$B$2),2) -> 454.5 | I10: =ROUND(G10*(1-Premissas!$B$6),2) -> 454.5 | J10: =Premissas!$B$3 -> 6 | K10: =ROUND(I10/J10,2) -> 75.75 | L10: PNEU 185/65R15 GOODYEAR EAGLE SPORT 2 88H | M10: 543.17 | N10: 477.99 | O10: 543.17 | P10: 12 | Q10: =IF(N10="","",ROUND(O10/P10,2)) -> 45.26 | R10: =IF(N10="","",1-N10/M10) -> 0.11999926 | S10: =IF(N10="","",1-O10/M10) -> 0 | T10: =IF(N10="","",H10/N10-1) -> -0.049143288 | U10: =IF(N10="","",I10/O10-1) -> -0.16324539 | V10: =IF(N10="","",K10/Q10-1) -> 0.67366328 | W10: =IF(T10="","Sem dado",IF(T10>Premissas!$B$4,"Caro",IF(T10<-Premissas!$B$4,"Competitivo","Na média"))) -> Na média | X10: print Lucas 23/09

Sheet Base_Consolidada
A1: item | B1: medida | C1: modelo | D1: sku_roma | E1: data_coleta | F1: concorrente | G1: roma_preco_cheio | H1: roma_preco_pix | I1: roma_preco_parcelado | J1: roma_n_parcelas | K1: roma_valor_parcela | L1: nome_anuncio_concorrente | M1: conc_preco_cheio | N1: conc_preco_pix | O1: conc_preco_parcelado | P1: conc_n_parcelas | Q1: conc_valor_parcela | R1: conc_desconto_pix_pct | S1: conc_desconto_parcelado_pct | T1: dif_pix_pct | U1: dif_parcelado_pct | V1: dif_parcela_pct | W1: classificacao_pix
A2: 1 | B2: 175/65R14 | C2: Kelly Edge Touring 2 | D2: 924096 | E2: 2026-09-23 | F2: PneuStore | G2: 306.81 | H2: =ROUND(G2*(1-Premissas!$B$2),2) -> 288.4 | I2: =ROUND(G2*(1-Premissas!$B$6),2) -> 288.4 | J2: =Premissas!$B$3 -> 6 | K2: =ROUND(I2/J2,2) -> 48.07 | L2: Pneu Kelly by Goodyear Aro 14 Edge Touring 2 175/65R14 86H XL | M2: 355.45 | N2: 319.9 | O2: 355.45 | P2: 10 | Q2: =IF(N2="","",ROUND(O2/P2,2)) -> 35.55 | R2: =IF(N2="","",1-N2/M2) -> 0.10001407 | S2: =IF(N2="","",1-O2/M2) -> 0 | T2: =IF(N2="","",H2/N2-1) -> -0.098468271 | U2: =IF(N2="","",I2/O2-1) -> -0.18863413 | V2: =IF(N2="","",K2/Q2-1) -> 0.35218003 | W2: =IF(T2="","Sem dado",IF(T2>Premissas!$B$4,"Caro",IF(T2<-Premissas!$B$4,"Competitivo","Na média"))) -> Competitivo
A3: 2 | B3: 185/60R15 | C3: Edge Sport 2 | D3: 1452 | E3: 2026-09-23 | F3: PneuStore | G3: 423.06 | H3: =ROUND(G3*(1-Premissas!$B$2),2) -> 397.68 | I3: =ROUND(G3*(1-Premissas!$B$6),2) -> 397.68 | J3: =Premissas!$B$3 -> 6 | K3: =ROUND(I3/J3,2) -> 66.28 | L3: Pneu Kelly by Goodyear Aro 15 Edge Sport 2 185/60R15 88H XL | M3: 481.59 | N3: 394.9 | O3: 481.59 | P3: 10 | Q3: =IF(N3="","",ROUND(O3/P3,2)) -> 48.16 | R3: =IF(N3="","",1-N3/M3) -> 0.18000789 | S3: =IF(N3="","",1-O3/M3) -> 0 | T3: =IF(N3="","",H3/N3-1) -> 0.0070397569 | U3: =IF(N3="","",I3/O3-1) -> -0.17423535 | V3: =IF(N3="","",K3/Q3-1) -> 0.37624585 | W3: =IF(T3="","Sem dado",IF(T3>Premissas!$B$4,"Caro",IF(T3<-Premissas!$B$4,"Competitivo","Na média"))) -> Na média
A4: 3 | B4: 205/65R16 | C4: EfficientGrip SUV | D4: 923983 | E4: 2026-09-23 | F4: PneuStore | G4: 619.29 | H4: =ROUND(G4*(1-Premissas!$B$2),2) -> 582.13 | I4: =ROUND(G4*(1-Premissas!$B$6),2) -> 582.13 | J4: =Premissas!$B$3 -> 6 | K4: =ROUND(I4/J4,2) -> 97.02 | L4: Pneu Goodyear Aro 16 EfficientGrip SUV 205/65R16 95H | M4: 755.45 | N4: 679.9 | O4: 755.45 | P4: 10 | Q4: =IF(N4="","",ROUND(O4/P4,2)) -> 75.55 | R4: =IF(N4="","",1-N4/M4) -> 0.10000662 | S4: =IF(N4="","",1-O4/M4) -> 0 | T4: =IF(N4="","",H4/N4-1) -> -0.14380056 | U4: =IF(N4="","",I4/O4-1) -> -0.22942617 | V4: =IF(N4="","",K4/Q4-1) -> 0.28418266 | W4: =IF(T4="","Sem dado",IF(T4>Premissas!$B$4,"Caro",IF(T4<-Premissas!$B$4,"Competitivo","Na média"))) -> Competitivo
A5: 4 | B5: 175/65R14 | C5: Assurance Maxlife | D5: 923865 | E5: 2026-09-23 | F5: PneuStore | G5: 353.31 | H5: =ROUND(G5*(1-Premissas!$B$2),2) -> 332.11 | I5: =ROUND(G5*(1-Premissas!$B$6),2) -> 332.11 | J5: =Premissas!$B$3 -> 6 | K5: =ROUND(I5/J5,2) -> 55.35 | L5: Pneu Goodyear Aro 14 Assurance Maxlife 175/65R14 86H XL | M5: 397.62 | N5: 349.9 | O5: 397.62 | P5: 10 | Q5: =IF(N5="","",ROUND(O5/P5,2)) -> 39.76 | R5: =IF(N5="","",1-N5/M5) -> 0.12001408 | S5: =IF(N5="","",1-O5/M5) -> 0 | T5: =IF(N5="","",H5/N5-1) -> -0.050843098 | U5: =IF(N5="","",I5/O5-1) -> -0.16475529 | V5: =IF(N5="","",K5/Q5-1) -> 0.39210262 | W5: =IF(T5="","Sem dado",IF(T5>Premissas!$B$4,"Caro",IF(T5<-Premissas!$B$4,"Competitivo","Na média"))) -> Competitivo
A6: 5 | B6: 175/70R13 | C6: Edge Touring 2 | D6: 924049 | E6: 2026-09-23 | F6: PneuStore | G6: 297.51 | H6: =ROUND(G6*(1-Premissas!$B$2),2) -> 279.66 | I6: =ROUND(G6*(1-Premissas!$B$6),2) -> 279.66 | J6: =Premissas!$B$3 -> 6 | K6: =ROUND(I6/J6,2) -> 46.61 | L6: Pneu Kelly By Goodyear Aro 13 Edge Touring 2 175/70R13 82T | M6: 340.8 | N6: 299.9 | O6: 340.8 | P6: 10 | Q6: =IF(N6="","",ROUND(O6/P6,2)) -> 34.08 | R6: =IF(N6="","",1-N6/M6) -> 0.12001174 | S6: =IF(N6="","",1-O6/M6) -> 0 | T6: =IF(N6="","",H6/N6-1) -> -0.067489163 | U6: =IF(N6="","",I6/O6-1) -> -0.17940141 | V6: =IF(N6="","",K6/Q6-1) -> 0.36766432 | W6: =IF(T6="","Sem dado",IF(T6>Premissas!$B$4,"Caro",IF(T6<-Premissas!$B$4,"Competitivo","Na média"))) -> Competitivo
A7: 6 | B7: 185/65R15 | C7: Edge Sport 2 | D7: 1445 | E7: 2026-09-23 | F7: PneuStore | G7: 433.29 | H7: =ROUND(G7*(1-Premissas!$B$2),2) -> 407.29 | I7: =ROUND(G7*(1-Premissas!$B$6),2) -> 407.29 | J7: =Premissas!$B$3 -> 6 | K7: =ROUND(I7/J7,2) -> 67.88 | L7: Pneu Kelly by Goodyear Aro 15 Edge Sport 2 185/65R15 88H | M7: 512.08 | N7: 419.9 | O7: 512.08 | P7: 10 | Q7: =IF(N7="","",ROUND(O7/P7,2)) -> 51.21 | R7: =IF(N7="","",1-N7/M7) -> 0.18001094 | S7: =IF(N7="","",1-O7/M7) -> 0 | T7: =IF(N7="","",H7/N7-1) -> -0.03003096 | U7: =IF(N7="","",I7/O7-1) -> -0.20463599 | V7: =IF(N7="","",K7/Q7-1) -> 0.32552236 | W7: =IF(T7="","Sem dado",IF(T7>Premissas!$B$4,"Caro",IF(T7<-Premissas!$B$4,"Competitivo","Na média"))) -> Na média
A8: 7 | B8: 225/75R16C | C8: Cargo Marathon 2 | D8: 923825 | E8: 2026-09-23 | F8: PneuStore | G8: 1097.31 | H8: =ROUND(G8*(1-Premissas!$B$2),2) -> 1031.47 | I8: =ROUND(G8*(1-Premissas!$B$6),2) -> 1031.47 | J8: =Premissas!$B$3 -> 6 | K8: =ROUND(I8/J8,2) -> 171.91 | L8: Pneu Goodyear Aro 16 Cargo Marathon 2 225/75R16C 118/116R 10 Lonas | M8: 1299.89 | N8: 1169.9 | O8: 1299.89 | P8: 10 | Q8: =IF(N8="","",ROUND(O8/P8,2)) -> 129.99 | R8: =IF(N8="","",1-N8/M8) -> 0.10000077 | S8: =IF(N8="","",1-O8/M8) -> 0 | T8: =IF(N8="","",H8/N8-1) -> -0.11832635 | U8: =IF(N8="","",I8/O8-1) -> -0.2064944 | V8: =IF(N8="","",K8/Q8-1) -> 0.32248635 | W8: =IF(T8="","Sem dado",IF(T8>Premissas!$B$4,"Caro",IF(T8<-Premissas!$B$4,"Competitivo","Na média"))) -> Competitivo
A9: 8 | B9: 215/55R17 | C9: EfficientGrip SUV | D9: 2081 | E9: 2026-09-23 | F9: PneuStore | G9: 702.99 | H9: =ROUND(G9*(1-Premissas!$B$2),2) -> 660.81 | I9: =ROUND(G9*(1-Premissas!$B$6),2) -> 660.81 | J9: =Premissas!$B$3 -> 6 | K9: =ROUND(I9/J9,2) -> 110.14 | L9: Pneu Goodyear Aro 17 EfficientGrip SUV 215/55R17 94V | M9: 749.89 | N9: 659.9 | O9: 749.89 | P9: 10 | Q9: =IF(N9="","",ROUND(O9/P9,2)) -> 74.99 | R9: =IF(N9="","",1-N9/M9) -> 0.12000427 | S9: =IF(N9="","",1-O9/M9) -> 0 | T9: =IF(N9="","",H9/N9-1) -> 0.0013789968 | U9: =IF(N9="","",I9/O9-1) -> -0.11879076 | V9: =IF(N9="","",K9/Q9-1) -> 0.46872916 | W9: =IF(T9="","Sem dado",IF(T9>Premissas!$B$4,"Caro",IF(T9<-Premissas!$B$4,"Competitivo","Na média"))) -> Na média
A10: 9 | B10: 185/65R15 | C10: Eagle Sport 2 | D10: 923978 | E10: 2026-09-23 | F10: PneuStore | G10: 483.51 | H10: =ROUND(G10*(1-Premissas!$B$2),2) -> 454.5 | I10: =ROUND(G10*(1-Premissas!$B$6),2) -> 454.5 | J10: =Premissas!$B$3 -> 6 | K10: =ROUND(I10/J10,2) -> 75.75 | L10: Pneu Goodyear Aro 15 Eagle Sport 2 185/65R15 88H | M10: 533.23 | N10: 479.9 | O10: 533.23 | P10: 10 | Q10: =IF(N10="","",ROUND(O10/P10,2)) -> 53.32 | R10: =IF(N10="","",1-N10/M10) -> 0.10001313 | S10: =IF(N10="","",1-O10/M10) -> 0 | T10: =IF(N10="","",H10/N10-1) -> -0.052927693 | U10: =IF(N10="","",I10/O10-1) -> -0.14764736 | V10: =IF(N10="","",K10/Q10-1) -> 0.42066767 | W10: =IF(T10="","Sem dado",IF(T10>Premissas!$B$4,"Caro",IF(T10<-Premissas!$B$4,"Competitivo","Na média"))) -> Competitivo
A11: 1 | B11: 175/65R14 | C11: Kelly Edge Touring 2 | D11: 924096 | E11: 2026-09-23 | F11: HC Pneus | G11: 306.81 | H11: =ROUND(G11*(1-Premissas!$B$2),2) -> 288.4 | I11: =ROUND(G11*(1-Premissas!$B$6),2) -> 288.4 | J11: =Premissas!$B$3 -> 6 | K11: =ROUND(I11/J11,2) -> 48.07 | L11: Pneu 175/65R14 86H Goodyear Kelly Edge Touring 2 | M11: 435.72 | N11: 338.12 | O11: 348.58 | P11: 6 | Q11: =IF(N11="","",ROUND(O11/P11,2)) -> 58.1 | R11: =IF(N11="","",1-N11/M11) -> 0.22399706 | S11: =IF(N11="","",1-O11/M11) -> 0.19999082 | T11: =IF(N11="","",H11/N11-1) -> -0.14704839 | U11: =IF(N11="","",I11/O11-1) -> -0.1726433 | V11: =IF(N11="","",K11/Q11-1) -> -0.17263339 | W11: =IF(T11="","Sem dado",IF(T11>Premissas!$B$4,"Caro",IF(T11<-Premissas!$B$4,"Competitivo","Na média"))) -> Competitivo
A12: 2 | B12: 185/60R15 | C12: Edge Sport 2 | D12: 1452 | E12: 2026-09-23 | F12: HC Pneus | G12: 423.06 | H12: =ROUND(G12*(1-Premissas!$B$2),2) -> 397.68 | I12: =ROUND(G12*(1-Premissas!$B$6),2) -> 397.68 | J12: =Premissas!$B$3 -> 6 | K12: =ROUND(I12/J12,2) -> 66.28 | L12: Pneu 185/60R15 88H Goodyear Kelly Edge Sport 2 | M12: 583.62 | N12: 452.89 | O12: 466.9 | P12: 6 | Q12: =IF(N12="","",ROUND(O12/P12,2)) -> 77.82 | R12: =IF(N12="","",1-N12/M12) -> 0.22399849 | S12: =IF(N12="","",1-O12/M12) -> 0.19999315 | T12: =IF(N12="","",H12/N12-1) -> -0.12190598 | U12: =IF(N12="","",I12/O12-1) -> -0.14825444 | V12: =IF(N12="","",K12/Q12-1) -> -0.14829093 | W12: =IF(T12="","Sem dado",IF(T12>Premissas!$B$4,"Caro",IF(T12<-Premissas!$B$4,"Competitivo","Na média"))) -> Competitivo
A13: 3 | B13: 205/65R16 | C13: EfficientGrip SUV | D13: 923983 | E13: 2026-09-23 | F13: HC Pneus | G13: 619.29 | H13: =ROUND(G13*(1-Premissas!$B$2),2) -> 582.13 | I13: =ROUND(G13*(1-Premissas!$B$6),2) -> 582.13 | J13: =Premissas!$B$3 -> 6 | K13: =ROUND(I13/J13,2) -> 97.02 | L13: Pneu 205/65R16 95H Goodyear EfficientGrip SUV | M13: 847.48 | N13: 657.64 | O13: 677.98 | P13: 6 | Q13: =IF(N13="","",ROUND(O13/P13,2)) -> 113 | R13: =IF(N13="","",1-N13/M13) -> 0.22400529 | S13: =IF(N13="","",1-O13/M13) -> 0.20000472 | T13: =IF(N13="","",H13/N13-1) -> -0.11481966 | U13: =IF(N13="","",I13/O13-1) -> -0.14137585 | V13: =IF(N13="","",K13/Q13-1) -> -0.14141593 | W13: =IF(T13="","Sem dado",IF(T13>Premissas!$B$4,"Caro",IF(T13<-Premissas!$B$4,"Competitivo","Na média"))) -> Competitivo
... A28: 9 | B28: 185/65R15 | C28: Eagle Sport 2 | D28: 923978 | E28: 2026-09-23 | F28: Achei Pneus | G28: 483.51 | H28: =ROUND(G28*(1-Premissas!$B$2),2) -> 454.5 | I28: =ROUND(G28*(1-Premissas!$B$6),2) -> 454.5 | J28: =Premissas!$B$3 -> 6 | K28: =ROUND(I28/J28,2) -> 75.75 | L28: PNEU 185/65R15 GOODYEAR EAGLE SPORT 2 88H | M28: 543.17 | N28: 477.99 | O28: 543.17 | P28: 12 | Q28: =IF(N28="","",ROUND(O28/P28,2)) -> 45.26 | R28: =IF(N28="","",1-N28/M28) -> 0.11999926 | S28: =IF(N28="","",1-O28/M28) -> 0 | T28: =IF(N28="","",H28/N28-1) -> -0.049143288 | U28: =IF(N28="","",I28/O28-1) -> -0.16324539 | V28: =IF(N28="","",K28/Q28-1) -> 0.67366328 | W28: =IF(T28="","Sem dado",IF(T28>Premissas!$B$4,"Caro",IF(T28<-Premissas!$B$4,"Competitivo","Na média"))) -> Na média
